MANIFEST.in
README.md
setup.cfg
setup.py
TemplateNestCpp/TemplateNest.sln
TemplateNestCpp/reg.p6
TemplateNestCpp/.vs/TemplateNest/v16/.suo
TemplateNestCpp/.vs/TemplateNest/v16/Browse.VC.db-shm
TemplateNestCpp/.vs/TemplateNest/v16/Browse.VC.db-wal
TemplateNestCpp/.vs/TemplateNest/v16/Browse.VC.opendb
TemplateNestCpp/.vs/TemplateNest/v16/Solution.VC.db-shm
TemplateNestCpp/.vs/TemplateNest/v16/Solution.VC.db-wal
TemplateNestCpp/ConsoleApplication1/ConsoleApplication1.cpp
TemplateNestCpp/ConsoleApplication1/ConsoleApplication1.vcxproj
TemplateNestCpp/ConsoleApplication1/ConsoleApplication1.vcxproj.filters
TemplateNestCpp/ConsoleApplication1/ConsoleApplication1.vcxproj.user
TemplateNestCpp/ConsoleApplication1/TemplateNestClass.cpp
TemplateNestCpp/ConsoleApplication1/TemplateNestClass.cpp.bak
TemplateNestCpp/ConsoleApplication1/TemplateNestClass.h
TemplateNestCpp/ConsoleApplication1/Debug/ConsoleApplication1.exe.recipe
TemplateNestCpp/ConsoleApplication1/Debug/ConsoleApplication1.log
TemplateNestCpp/ConsoleApplication1/Debug/ConsoleApplication1.vcxproj.FileListAbsolute.txt
TemplateNestCpp/ConsoleApplication1/Debug/TestTemplateNest.Build.CppClean.log
TemplateNestCpp/ConsoleApplication1/Debug/TestTemplateNest.exe.recipe
TemplateNestCpp/ConsoleApplication1/Debug/ConsoleA.23be33ea.tlog/ConsoleApplication1.lastbuildstate
TemplateNestCpp/ConsoleApplication1/Debug/TestTemplateNest.tlog/TestTemplateNest.lastbuildstate
TemplateNestCpp/ConsoleApplication1/rapidjson/allocators.h
TemplateNestCpp/ConsoleApplication1/rapidjson/cursorstreamwrapper.h
TemplateNestCpp/ConsoleApplication1/rapidjson/document.h
TemplateNestCpp/ConsoleApplication1/rapidjson/encodedstream.h
TemplateNestCpp/ConsoleApplication1/rapidjson/encodings.h
TemplateNestCpp/ConsoleApplication1/rapidjson/filereadstream.h
TemplateNestCpp/ConsoleApplication1/rapidjson/filewritestream.h
TemplateNestCpp/ConsoleApplication1/rapidjson/fwd.h
TemplateNestCpp/ConsoleApplication1/rapidjson/istreamwrapper.h
template_nestdll.egg-info/PKG-INFO
template_nestdll.egg-info/SOURCES.txt
template_nestdll.egg-info/dependency_links.txt
template_nestdll.egg-info/top_level.txt
