Metadata-Version: 2.1
Name: template-nestdll
Version: 1.0.1
Summary: Represent a nested structure of templates in a dict
Home-page: UNKNOWN
Author: Tom Gracey
Author-email: tomgracey@gmail.com
License: MIT
Platform: UNKNOWN
Classifier: License :: OSI Approved :: MIT License
Classifier: Programming Language :: Python :: 3
Classifier: Programming Language :: Python :: 3.6
